hanapy/__init__.py
hanapy/core/__init__.py
hanapy/core/action.py
hanapy/core/card.py
hanapy/core/deck.py
hanapy/core/errors.py
hanapy/core/loop.py
hanapy/core/player.py
hanapy/core/state.py
hanapy/players/__init__.py
hanapy/players/dummy.py
hanapy/variants/__init__.py
hanapy/variants/classic.py
hanapy-0.0.1.dist-info/LICENSE
hanapy-0.0.1.dist-info/METADATA
hanapy-0.0.1.dist-info/WHEEL
hanapy-0.0.1.dist-info/RECORD
