Metadata-Version: 2.1
Name: hanapy
Version: 0.0.1
Summary: Hanabi engine for python
Home-page: https://github.com/mike0sv/hanapy
Author: mike0sv
Author-email: mike0sv@gmail.com
Requires-Python: >=3.8,<4.0
Classifier: Programming Language :: Python :: 3
Classifier: Programming Language :: Python :: 3.8
Classifier: Programming Language :: Python :: 3.9
Classifier: Programming Language :: Python :: 3.10
Classifier: Programming Language :: Python :: 3.11
Classifier: Programming Language :: Python :: 3.12
Project-URL: Documentation, https://mike0sv.github.io/hanapy/
Project-URL: Repository, https://github.com/mike0sv/hanapy
